langchain_azure_ai_inference_plus/__init__.py
langchain_azure_ai_inference_plus-1.0.5.dist-info/licenses/LICENSE
langchain_azure_ai_inference_plus-1.0.5.dist-info/METADATA
langchain_azure_ai_inference_plus-1.0.5.dist-info/WHEEL
langchain_azure_ai_inference_plus-1.0.5.dist-info/top_level.txt
langchain_azure_ai_inference_plus-1.0.5.dist-info/RECORD
